{"type": "plant", "seed": "sociocultural", "domain": "ontology", "endWord": "anticipatory", "results": ["sociocultural|anthropology", "/ethnology", "descriptive|ethnology", "explanatory\\", "intellectual|explanatory", "    cerebral\\", "cerebral|cortex", "/pallium", "ecclesiastical|pallium", "  ecclesiastic\\", "ecclesiastic|realms", "/spheres", "homogeneous|spheres", "      solid\\", "solid|matrix", "/template", "theoretical|template", " hypothetic\\", "antecedent|hypothetic", "anticipatory\\"]}